preprocess/CheckFile.py
preprocess/CreateTables.py
preprocess/SaveClassInfo.py
preprocess/TestPerformance.py
preprocess/UpdateImageInfo.py
preprocess/__init__.py
sparkpreprocess/__init__.py
sparkpreprocess/sparkpreprocess.py
openImagePreprocessing-1.0.1.dist-info/LICENSE
openImagePreprocessing-1.0.1.dist-info/METADATA
openImagePreprocessing-1.0.1.dist-info/WHEEL
openImagePreprocessing-1.0.1.dist-info/top_level.txt
openImagePreprocessing-1.0.1.dist-info/RECORD
