Metadata-Version: 2.1
Name: openImagePreprocessing
Version: 1.0.1
Summary: Preprocess functions for the Open Image Dataset.
Home-page: https://dev.azure.com/zhenwan/zhenwan_default/_git/AMLProjects
Author: zhenwan,t-zhiwan,t-tozho
Author-email: zhenwan@microsoft.com,t-zhiwan@microsoft.com,t-tozho@microsoft.com
License: UNKNOWN
Platform: UNKNOWN
Classifier: Programming Language :: Python :: 3
Classifier: License :: OSI Approved :: MIT License
Classifier: Operating System :: OS Independent
Requires-Dist: pandas
Requires-Dist: numpy
Requires-Dist: azure-storage-blob
Requires-Dist: opencv-contrib-python
Requires-Dist: Pillow
